wam_api/README.md
wam_api/_init_.py
wam_api/interpolator.py
wam_api/lru_cache.py
wam_api/requirements.txt
wam_api/wam_interpolate.py
wam_api-0.0.1.dist-info/METADATA
wam_api-0.0.1.dist-info/WHEEL
wam_api-0.0.1.dist-info/licenses/LICENSE
wam_api-0.0.1.dist-info/RECORD
