Metadata-Version: 2.3
Name: wam_api
Version: 0.0.1
Summary: This package allows users to input time (UT) and satellite locations and output the density value based on various WAM outputs.
Project-URL: NOAA SWCC Website, https://www.swpc.noaa.gov/
Project-URL: Learn about WAM_IPE here:, https://www.swpc.noaa.gov/products/wam-ipe
Author: Atheesh Thirumalairajan, Gili Gordiyenko, Anusha Iyer, Scott Chen, Varun Kota, Arav Luthra
License-File: LICENSE
Classifier: License :: Other/Proprietary License
Classifier: Operating System :: OS Independent
Classifier: Programming Language :: Python :: 3
Requires-Python: >=3.8
